cryptocmp/__init__.py
cryptocmp/coin.py
cryptocmp/coin_pair.py
cryptocmp/decorators.py
cryptocmp/exceptions.py
cryptocmp/test_coin.py
cryptocmp/test_coin_pair.py
cryptocmp/api/__init__.py
cryptocmp/api/coinlist.py
cryptocmp/api/test_coinlist.py
cryptocmp/api/historical/__init__.py
cryptocmp/api/historical/price/__init__.py
cryptocmp/api/historical/price/days.py
cryptocmp/api/historical/price/hours.py
cryptocmp/api/historical/price/minutes.py
cryptocmp/api/historical/price/test_days.py
cryptocmp/api/historical/price/test_hours.py
cryptocmp/api/historical/price/test_minutes.py
cryptocmp/api/price/__init__.py
cryptocmp/api/price/multiple.py
cryptocmp/api/price/single.py
cryptocmp/api/price/test_multiple.py
cryptocmp/api/price/test_single.py
cryptocmp-0.3.3.dist-info/METADATA
cryptocmp-0.3.3.dist-info/RECORD
cryptocmp-0.3.3.dist-info/WHEEL
cryptocmp-0.3.3.dist-info/top_level.txt
