Metadata-Version: 2.1
Name: cryptocmp
Version: 0.3.3
Summary: Python3 Wrapper for CryptoCompare public API
Home-page: https://github.com/OkThought/cryptocmp
Author: Ivan Bogush
Author-email: bogush.vano@gmail.com
License: MIT license
Keywords: cryptocmp
Platform: UNKNOWN
Classifier: Intended Audience :: Developers
Classifier: License :: OSI Approved :: MIT License
Classifier: Natural Language :: English
Classifier: Programming Language :: Python :: 3
Classifier: Programming Language :: Python :: 3.4
Classifier: Programming Language :: Python :: 3.5
Classifier: Programming Language :: Python :: 3.6
Classifier: Programming Language :: Python :: 3.7
Requires-Dist: requests
